frazzle/__init__.py
frazzle/__main__.py
frazzle/client.py
frazzle-0.2.2.dist-info/entry_points.txt
frazzle-0.2.2.dist-info/METADATA
frazzle-0.2.2.dist-info/WHEEL
frazzle-0.2.2.dist-info/RECORD
