Metadata-Version: 2.1
Name: frazzle
Version: 0.2.2
Summary: 
License: All rights reserved.
Author: Daniel DeFreez
Author-email: defreezd@sou.edu
Requires-Python: >=3.10,<3.12
Classifier: License :: Other/Proprietary License
Classifier: Programming Language :: Python :: 3
Classifier: Programming Language :: Python :: 3.10
Classifier: Programming Language :: Python :: 3.11
Requires-Dist: google-api-python-client (>=2.86.0,<3.0.0)
Requires-Dist: google-auth (>=2.17.3,<3.0.0)
Requires-Dist: google-auth-httplib2 (>=0.1.0,<0.2.0)
Requires-Dist: google-cloud-logging (>=3.5.0,<4.0.0)
Requires-Dist: langchain (>=0.0.146,<0.0.147)
Requires-Dist: openai (>=0.27.4,<0.28.0)
